Metadata-Version: 2.0
Name: keras-retinanet
Version: 0.3.1
Summary: Keras implementation of RetinaNet object detection.
Home-page: https://github.com/fizyr/keras-retinanet
Author: Hans Gaiser
Author-email: h.gaiser@fizyr.com
Maintainer: Hans Gaiser
Maintainer-email: h.gaiser@fizyr.com
License: UNKNOWN
Platform: UNKNOWN
Requires-Dist: keras
Requires-Dist: keras-resnet
Requires-Dist: scipy
Requires-Dist: six
